{
    "colors": [
        {
            "id": "default",
            "light": {
                "surface": [
                    "hsl(0deg 0% 100%)"
                ],
                "onSurface": [
                    "hsl(0deg 0% 10%)"
                ],
                "accent": [
                    {
                        "surface": [
                            "hsl(38.82deg 100% 50%)"
                        ],
                        "onSurface": [
                            "hsl(0deg 0% 0%)"
                        ]
                    }
                ],
                "error": [
                    {
                        "surface": [
                            "hsl(0deg 67.92% 41.57%)"
                        ],
                        "onSurface": [
                            "hsl(0deg 0% 0%)"
                        ]
                    }
                ],
                "secondary": [
                    {
                        "surface": [
                            "hsl(0deg 0% 40%)"
                        ],
                        "onSurface": [
                            "hsl(0deg 0% 100%)"
                        ]
                    }
                ]
            },
            "dark": {
                "surface": [
                    "hsl(0deg 0% 10%)"
                ],
                "onSurface": [
                    "hsl(0deg 0% 100%)"
                ],
                "accent": [
                    {
                        "surface": [
                            "hsl(32.94deg 100% 50%)"
                        ],
                        "onSurface": [
                            "hsl(0deg 0% 0%)"
                        ]
                    }
                ],
                "error": [
                    {
                        "surface": [
                            "hsl(0deg 67.92% 41.57%)"
                        ],
                        "onSurface": [
                            "hsl(0deg 0% 0%)"
                        ]
                    }
                ],
                "secondary": [
                    {
                        "surface": [
                            "hsl(0deg 0% 100%)"
                        ],
                        "onSurface": [
                            "hsl(0deg 0% 20%)"
                        ]
                    }
                ]
            }
        },
        {
            "id": "alt",
            "light": {
                "surface": [
                    "hsl(0deg 0% 93.73%)"
                ],
                "onSurface": [
                    "hsl(0deg 0% 0%)"
                ],
                "accent": [
                    {
                        "surface": [
                            "hsl(38.82deg 100% 50%)"
                        ],
                        "onSurface": [
                            "hsl(0deg 0% 0%)"
                        ]
                    }
                ],
                "error": [
                    {
                        "surface": [
                            "hsl(0deg 67.92% 41.57%)"
                        ],
                        "onSurface": [
                            "hsl(0deg 0% 0%)"
                        ]
                    }
                ]
            },
            "dark": {
                "surface": [
                    "hsl(0deg 0% 10%)"
                ],
                "onSurface": [
                    "hsl(0deg 0% 100%)"
                ],
                "accent": [
                    {
                        "surface": [
                            "hsl(32.94deg 100% 50%)"
                        ],
                        "onSurface": [
                            "hsl(0deg 0% 0%)"
                        ]
                    }
                ],
                "error": [
                    {
                        "surface": [
                            "hsl(0deg 67.92% 41.57%)"
                        ],
                        "onSurface": [
                            "hsl(0deg 0% 0%)"
                        ]
                    }
                ]
            }
        },
        {
            "id": "alt2",
            "light": {
                "surface": [
                    "hsl(0deg 0% 86.67%)"
                ],
                "onSurface": [
                    "hsl(0deg 0% 0%)"
                ],
                "accent": [
                    {
                        "surface": [
                            "hsl(38.82deg 100% 50%)"
                        ],
                        "onSurface": [
                            "hsl(0deg 0% 0%)"
                        ]
                    }
                ],
                "error": [
                    {
                        "surface": [
                            "hsl(0deg 67.92% 41.57%)"
                        ],
                        "onSurface": [
                            "hsl(0deg 0% 0%)"
                        ]
                    }
                ]
            },
            "dark": {
                "surface": [
                    "hsl(0deg 0% 20%)"
                ],
                "onSurface": [
                    "hsl(0deg 0% 100%)"
                ],
                "accent": [
                    {
                        "surface": [
                            "hsl(32.94deg 100% 50%)"
                        ],
                        "onSurface": [
                            "hsl(0deg 0% 0%)"
                        ]
                    }
                ],
                "error": [
                    {
                        "surface": [
                            "hsl(0deg 67.92% 41.57%)"
                        ],
                        "onSurface": [
                            "hsl(0deg 0% 0%)"
                        ]
                    }
                ]
            }
        },
        {
            "id": "highlight",
            "light": {
                "surface": [
                    "hsl(38.82deg 100% 50%)"
                ],
                "onSurface": [
                    "hsl(0deg 0% 0%)"
                ],
                "accent": [
                    {
                        "surface": [
                            "hsl(0deg 0% 100%)"
                        ],
                        "onSurface": [
                            "hsl(38.82deg 100% 50%)"
                        ]
                    }
                ]
            },
            "dark": {
                "surface": [
                    "hsl(32.94deg 100% 50%)"
                ],
                "onSurface": [
                    "hsl(0deg 0% 0%)"
                ],
                "accent": [
                    {
                        "surface": [
                            "hsl(0deg 0% 0%)"
                        ],
                        "onSurface": [
                            "hsl(0deg 0% 100%)"
                        ]
                    }
                ]
            }
        },
        {
            "id": "highlight-alt",
            "light": {
                "surface": [
                    "hsl(209.6deg 100% 55.88%)"
                ],
                "onSurface": [
                    "hsl(0deg 0% 0%)"
                ],
                "accent": [
                    {
                        "surface": [
                            "hsl(0deg 0% 100%)"
                        ],
                        "onSurface": [
                            "hsl(0deg 0% 0%)"
                        ]
                    }
                ]
            },
            "dark": {
                "surface": [
                    "hsl(225deg 72.73% 56.86%)"
                ],
                "onSurface": [
                    "hsl(0deg 0% 100%)"
                ],
                "accent": [
                    {
                        "surface": [
                            "hsl(0deg 0% 100%)"
                        ],
                        "onSurface": [
                            "hsl(0deg 0% 0%)"
                        ]
                    }
                ]
            }
        }
    ]
}